sdk/__init__.py
sdk/run.py
sdk/setup.py
sdk/test_hander_perf.py
sdk/apis/__init__.py
sdk/apis/build.py
sdk/apis/client.py
sdk/apis/pdu.py
sdk/apis/perf.py
sdk/apis/pr.py
sdk/config/__init__.py
sdk/config/develop.py
sdk/config/prod.py
sdk/handles/__init__.py
sdk/handles/build.py
sdk/handles/pdu.py
sdk/handles/perf.py
sdk/handles/pr.py
sdk/schemas/__init__.py
sdk/schemas/jenkins.py
sdk/schemas/pull_request.py
sdk/schemas/pull_request_job.py
sdk/schemas/test_case.py
sdk/utils/__init__.py
sdk/utils/csv_utils.py
sdk/utils/file_utils.py
sdk/utils/json_utils.py
sdk/utils/pd_utils.py
sdk/utils/xml_utils.py
web_api/__init__.py
web_api/exception.py
web_api/main.py
web_api/mongo.py
web_api/mysql.py
web_api/apis/__init__.py
web_api/apis/client.py
web_api/apis/hr.py
web_api/apis/pdu.py
web_api/config/__init__.py
web_api/config/develop.py
web_api/config/prod.py
web_api/handles/__init__.py
web_api/handles/build.py
web_api/handles/component.py
web_api/handles/perf.py
web_api/handles/pull_request.py
web_api/handles/pull_request_job.py
web_api/handles/test_case.py
web_api/models/Component.py
web_api/models/JenkinsResult.py
web_api/models/PullRequest.py
web_api/models/PullRequestJob.py
web_api/models/TestCase.py
web_api/models/__init__.py
web_api/models/perfResult.py
web_api/routers/__init__.py
web_api/routers/build.py
web_api/routers/component.py
web_api/routers/perf.py
web_api/routers/pull_request.py
web_api/routers/pull_request_job.py
web_api/routers/test_case.py
web_api/schemas/__init__.py
web_api/schemas/component.py
web_api/schemas/hr.py
web_api/schemas/jenkins.py
web_api/schemas/perf.py
web_api/schemas/pull_request.py
web_api/schemas/pull_request_job.py
web_api/schemas/test_case.py
web_api/utils/__init__.py
web_api/utils/dict_utils.py
web_api/utils/log.py
web_api/utils/resp.py
br_ci_cmd-1.0.dist-info/METADATA
br_ci_cmd-1.0.dist-info/WHEEL
br_ci_cmd-1.0.dist-info/top_level.txt
br_ci_cmd-1.0.dist-info/RECORD
