Metadata-Version: 2.1
Name: br-ci-cmd
Version: 1.0
Summary: Birentech CI command
Home-page: UNKNOWN
Author: Gliu
Author-email: Gliu@test.com
License: UNKNOWN
Platform: UNKNOWN
